convert2geojson/__init__.py
convert2geojson/base.py
convert2geojson/shapes.py
convert2geojson/html/template/clusterpies.css
convert2geojson/html/template/index.html
convert2geojson-0.0.2.dist-info/DESCRIPTION.rst
convert2geojson-0.0.2.dist-info/METADATA
convert2geojson-0.0.2.dist-info/RECORD
convert2geojson-0.0.2.dist-info/WHEEL
convert2geojson-0.0.2.dist-info/metadata.json
convert2geojson-0.0.2.dist-info/top_level.txt
