Metadata-Version: 2.0
Name: convert2geojson
Version: 0.0.2
Summary: Tools for converting dataframes to GeoJSON format.
Home-page: https://github.com/computational-antiquity/convert2geojson/
Author: Malte Vogl
Author-email: mvogl@mpiwg-berlin.mpg.de
License: GPLv3
Project-URL: Home, https://github.com/computational-antiquity/convert2geojson/
Project-URL: Tracker, https://github.com/computational-antiquity/convert2geojson/issues
Project-URL: Download, https://github.com/computational-antiquity/convert2geojson/archive/0.0.2.tar.gz
Platform: UNKNOWN
Classifier: Development Status :: 3 - Alpha
Classifier: Intended Audience :: Science/Research
Classifier: Topic :: Text Processing :: General
Classifier: Topic :: Text Processing :: Indexing
Classifier: License :: OSI Approved :: GNU General Public License v3 (GPLv3)
Classifier: Programming Language :: Python :: 3
Requires-Python: >=3
Requires-Dist: pandas
Requires-Dist: xlrd
Requires-Dist: citableclass
Requires-Dist: ipyleaflet
Requires-Dist: ipywidgets
Requires-Dist: jinja2
Requires-Dist: ipython
